sim/ConfigurationRegister/ConfigRegVRTL.v
`ifndef CONFIG_REG_V
`define CONFIG_REG_V
module ConfigRegVRTL
#(
  // Parameters
  parameter ADDR_SIZE    = 4,
  parameter PAYLOAD_SIZE = 8,
  parameter CONFIG_ADDR  = 4'b0000
)(
  // I/O
  input logic clk,
  input logic reset,
  //input logic recv_val,
	//output logic recv_rdy,
	//output logic send_val,
	//input logic send_rdy,
  input logic [ADDR_SIZE + PAYLOAD_SIZE:0] rec_msg,
  output logic [ADDR_SIZE + PAYLOAD_SIZE:0] send_msg
);

  // Local Variables
  logic [ADDR_SIZE - 1:0] addr;
  logic write;
  logic success;
  logic [PAYLOAD_SIZE - 1:0] payload;

  // Register
  always @(posedge clk) begin
    if (reset) begin
      //recv_rdy <= 1;
      //send_val <= 0;
      send_msg <= '0;
    end
    else begin
      send_msg <= {addr, success, payload};
      //recv_rdy <= 0;
      //send_val <= 0;
    end
  end

  // Control
  always @(*) begin
    if(rec_msg[ADDR_SIZE + PAYLOAD_SIZE: PAYLOAD_SIZE + 1] 
       == CONFIG_ADDR && rec_msg[PAYLOAD_SIZE]) begin
      addr = rec_msg[ADDR_SIZE + PAYLOAD_SIZE: PAYLOAD_SIZE + 1];
      success = 1'b1;
      payload = rec_msg[PAYLOAD_SIZE - 1:0]; 
    end
    else begin
      addr = '0;
      success = 1'b0;
      payload = '0; end
  end
endmodule
`endif

sim/ConfigurationRegister/ConfigRegVRTLTest.v
`include "ConfigRegVRTL.v"

// iverilog -g2012 -o ConfigRegVRTLTest ConfigRegVRTLTest.v

module top;
  parameter ADDR_SIZE    = 4;
  parameter PAYLOAD_SIZE = 8;

  logic clk = 1;
  always #5 clk = ~clk;

  logic reset;
  logic [ADDR_SIZE + PAYLOAD_SIZE:0] rec_msg;
  logic [ADDR_SIZE + PAYLOAD_SIZE:0] send_msg;

  ConfigRegVRTL #(.ADDR_SIZE(ADDR_SIZE)) config_reg
  (
    .clk(clk),
    .reset(reset),
    .rec_msg(rec_msg),
    .send_msg(send_msg)
  );

  initial begin
    $dumpfile("ConfigRegVRTLTest.vcd");
    $dumpvars;
  
  reset = 1'b1;
  rec_msg = 13'b0000111111111;
  #11;      
  $display( "TEST 1 (reset): rec_msg = %b,  send_msg= %b"
  , rec_msg, send_msg);

  reset = 1'b0;
  rec_msg = 13'b0000101010101;
  #10;
  $display( "TEST 2 (addr matches, write): rec_msg = %b,  send_msg= %b"
  , rec_msg, send_msg);

  reset = 1'b0;
  rec_msg = 13'b0000001010101;
  #10;
  $display( "TEST 3 (addr matches, no write): rec_msg = %b,  send_msg= %b"
  , rec_msg, send_msg);

  reset = 1'b0;
  rec_msg = 13'b0101101010101;
  #10;
  $display( "TEST 4 (addr doesn't match, write): rec_msg = %b,  send_msg= %b"
  , rec_msg, send_msg);
  
  reset = 1'b0;
  rec_msg = 13'b0101001010101;
  #10;
  $display( "TEST 5 (addr doesn't match, no write): rec_msg = %b,  send_msg= %b"
  , rec_msg, send_msg);


  $finish;
  end

endmodule

sim/ConfigurationRegister/ConfigRegVRTLTest.vcd
$date
	Mon Apr 24 17:26:50 2023
$end
$version
	Icarus Verilog
$end
$timescale
	1s
$end
$scope module top $end
$var wire 13 ! send_msg [12:0] $end
$var parameter 32 " ADDR_SIZE $end
$var parameter 32 # PAYLOAD_SIZE $end
$var reg 1 $ clk $end
$var reg 13 % rec_msg [12:0] $end
$var reg 1 & reset $end
$scope module config_reg $end
$var wire 1 $ clk $end
$var wire 13 ' rec_msg [12:0] $end
$var wire 1 & reset $end
$var parameter 32 ( ADDR_SIZE $end
$var parameter 4 ) CONFIG_ADDR $end
$var parameter 32 * PAYLOAD_SIZE $end
$var reg 4 + addr [3:0] $end
$var reg 8 , payload [7:0] $end
$var reg 13 - send_msg [12:0] $end
$var reg 1 . success $end
$upscope $end
$upscope $end
$enddefinitions $end
$comment Show the parameter values. $end
$dumpall
b1000 *
b0 )
b100 (
b1000 #
b100 "
$end
#0
$dumpvars
1.
bx -
b11111111 ,
b0 +
b111111111 '
1&
b111111111 %
1$
bx !
$end
#5
0$
#10
b0 !
b0 -
1$
#11
b1010101 ,
b101010101 %
b101010101 '
0&
#15
0$
#20
b101010101 !
b101010101 -
1$
#21
b0 ,
0.
b1010101 %
b1010101 '
#25
0$
#30
b0 !
b0 -
1$
#31
b101101010101 %
b101101010101 '
#35
0$
#40
1$
#41
b101001010101 %
b101001010101 '
